GalleryThief/__init__.py
GalleryThief/mask.py
GalleryThief/performer.py
GalleryThief/strategies.py
gallery_thief-1.1.0.dist-info/LICENSE
gallery_thief-1.1.0.dist-info/METADATA
gallery_thief-1.1.0.dist-info/WHEEL
gallery_thief-1.1.0.dist-info/top_level.txt
gallery_thief-1.1.0.dist-info/RECORD
