Metadata-Version: 2.1
Name: gallery-thief
Version: 1.1.0
Summary: Simple python package for scraping images from different search engines by prompt.
Author-email: Kirill Voloshin <kirill.voloshin.98@ya.ru>
Project-URL: Homepage, https://github.com/viktor-akusoff/GalleryThief
Project-URL: Bug Tracker, https://github.com/viktor-akusoff/GalleryThief/issues
Classifier: Programming Language :: Python :: 3
Classifier: License :: OSI Approved :: MIT License
Classifier: Operating System :: OS Independent
Requires-Python: >=3.7
License-File: LICENSE
